{
  "validateUpsert": true,
  "properties": {
    "name": {
      "type": "string",
      "id": true,
      "json": false
    },
    "facetName": {
      "type": "string",
      "required": true,
      "json": false
    },
    "host": {
      "type": "string"
    },
    "port": {
      "type": "number"
    },
    "url": {
      "type": "string"
    },
    "database": {
      "type": "string"
    },
    "username": {
      "type": "string"
    },
    "password": {
      "type": "string"
    }
  },
  "public": true,
  "dataSource": "db",
  "http": {"path": "/Workspace/:workspaceId/DataSourceDefinition"}
}